return {
  { 0x00, "MOVE",     false, true,  "R", "N", "ABC"  };
  { 0x01, "LOADK",    false, true,  "K", "N", "ABx"  };
  { 0x02, "LOADKX",   false, true,  "N", "N", "ABx"  };
  { 0x03, "LOADBOOL", false, true,  "U", "U", "ABC"  };
  { 0x04, "LOADNIL",  false, true,  "U", "N", "ABC"  };
  { 0x05, "GETUPVAL", false, true,  "U", "N", "ABC"  };
  { 0x06, "GETTABUP", false, true,  "U", "K", "ABC"  };
  { 0x07, "GETTABLE", false, true,  "R", "K", "ABC"  };
  { 0x08, "SETTABUP", false, false, "K", "K", "ABC"  };
  { 0x09, "SETUPVAL", false, false, "U", "N", "ABC"  };
  { 0x0A, "SETTABLE", false, false, "K", "K", "ABC"  };
  { 0x0B, "NEWTABLE", false, true,  "U", "U", "ABC"  };
  { 0x0C, "SELF",     false, true,  "R", "K", "ABC"  };
  { 0x0D, "ADD",      false, true,  "K", "K", "ABC"  };
  { 0x0E, "SUB",      false, true,  "K", "K", "ABC"  };
  { 0x0F, "MUL",      false, true,  "K", "K", "ABC"  };
  { 0x10, "MOD",      false, true,  "K", "K", "ABC"  };
  { 0x11, "POW",      false, true,  "K", "K", "ABC"  };
  { 0x12, "DIV",      false, true,  "K", "K", "ABC"  };
  { 0x13, "IDIV",     false, true,  "K", "K", "ABC"  };
  { 0x14, "BAND",     false, true,  "K", "K", "ABC"  };
  { 0x15, "BOR",      false, true,  "K", "K", "ABC"  };
  { 0x16, "BXOR",     false, true,  "K", "K", "ABC"  };
  { 0x17, "SHL",      false, true,  "K", "K", "ABC"  };
  { 0x18, "SHR",      false, true,  "K", "K", "ABC"  };
  { 0x19, "UNM",      false, true,  "R", "N", "ABC"  };
  { 0x1A, "BNOT",     false, true,  "R", "N", "ABC"  };
  { 0x1B, "NOT",      false, true,  "R", "N", "ABC"  };
  { 0x1C, "LEN",      false, true,  "R", "N", "ABC"  };
  { 0x1D, "CONCAT",   false, true,  "R", "R", "ABC"  };
  { 0x1E, "JMP",      false, false, "R", "N", "AsBx" };
  { 0x1F, "EQ",       true,  false, "K", "K", "ABC"  };
  { 0x20, "LT",       true,  false, "K", "K", "ABC"  };
  { 0x21, "LE",       true,  false, "K", "K", "ABC"  };
  { 0x22, "TEST",     true,  false, "N", "U", "ABC"  };
  { 0x23, "TESTSET",  true,  true,  "R", "U", "ABC"  };
  { 0x24, "CALL",     false, true,  "U", "U", "ABC"  };
  { 0x25, "TAILCALL", false, true,  "U", "U", "ABC"  };
  { 0x26, "RETURN",   false, false, "U", "N", "ABC"  };
  { 0x27, "FORLOOP",  false, true,  "R", "N", "AsBx" };
  { 0x28, "FORPREP",  false, true,  "R", "N", "AsBx" };
  { 0x29, "TFORCALL", false, false, "N", "U", "ABC"  };
  { 0x2A, "TFORLOOP", false, true,  "R", "N", "AsBx" };
  { 0x2B, "SETLIST",  false, false, "U", "U", "ABC"  };
  { 0x2C, "CLOSURE",  false, true,  "U", "N", "ABx"  };
  { 0x2D, "VARARG",   false, true,  "U", "N", "ABC"  };
  { 0x2E, "EXTRAARG", false, false, "U", "U", "Ax"   };
}
