Name|5.1|T|A|B|C|Mode|5.2|T|A|B|C|Mode|5.3|T|A|B|C|Mode
----|----|----|----|----|----|----|----|----|----|----|----|----|----|----|----|----|----|----
MOVE|0|0|1|R|N|ABC|0|0|1|R|N|ABC|0|0|1|R|N|ABC
LOADK|1|0|1|K|N|ABx|1|0|1|K|N|ABx|1|0|1|K|N|ABx
LOADKX|||||||2|0|1|N|N|ABx|2|0|1|N|N|ABx
LOADBOOL|2|0|1|U|U|ABC|3|0|1|U|U|ABC|3|0|1|U|U|ABC
LOADNIL|3|0|1|R|N|ABC|4|0|1|U|N|ABC|4|0|1|U|N|ABC
GETUPVAL|4|0|1|U|N|ABC|5|0|1|U|N|ABC|5|0|1|U|N|ABC
GETTABUP|||||||6|0|1|U|K|ABC|6|0|1|U|K|ABC
GETTABLE|6|0|1|R|K|ABC|7|0|1|R|K|ABC|7|0|1|R|K|ABC
SETTABUP|||||||8|0|0|K|K|ABC|8|0|0|K|K|ABC
SETUPVAL|8|0|0|U|N|ABC|9|0|0|U|N|ABC|9|0|0|U|N|ABC
SETTABLE|9|0|0|K|K|ABC|10|0|0|K|K|ABC|10|0|0|K|K|ABC
NEWTABLE|10|0|1|U|U|ABC|11|0|1|U|U|ABC|11|0|1|U|U|ABC
SELF|11|0|1|R|K|ABC|12|0|1|R|K|ABC|12|0|1|R|K|ABC
ADD|12|0|1|K|K|ABC|13|0|1|K|K|ABC|13|0|1|K|K|ABC
SUB|13|0|1|K|K|ABC|14|0|1|K|K|ABC|14|0|1|K|K|ABC
MUL|14|0|1|K|K|ABC|15|0|1|K|K|ABC|15|0|1|K|K|ABC
MOD|16|0|1|K|K|ABC|17|0|1|K|K|ABC|16|0|1|K|K|ABC
POW|17|0|1|K|K|ABC|18|0|1|K|K|ABC|17|0|1|K|K|ABC
DIV|15|0|1|K|K|ABC|16|0|1|K|K|ABC|18|0|1|K|K|ABC
IDIV|||||||||||||19|0|1|K|K|ABC
BAND|||||||||||||20|0|1|K|K|ABC
BOR|||||||||||||21|0|1|K|K|ABC
BXOR|||||||||||||22|0|1|K|K|ABC
SHL|||||||||||||23|0|1|K|K|ABC
SHR|||||||||||||24|0|1|K|K|ABC
UNM|18|0|1|R|N|ABC|19|0|1|R|N|ABC|25|0|1|R|N|ABC
BNOT|||||||||||||26|0|1|R|N|ABC
NOT|19|0|1|R|N|ABC|20|0|1|R|N|ABC|27|0|1|R|N|ABC
LEN|20|0|1|R|N|ABC|21|0|1|R|N|ABC|28|0|1|R|N|ABC
CONCAT|21|0|1|R|R|ABC|22|0|1|R|R|ABC|29|0|1|R|R|ABC
JMP|22|0|0|R|N|AsBx|23|0|0|R|N|AsBx|30|0|0|R|N|AsBx
EQ|23|1|0|K|K|ABC|24|1|0|K|K|ABC|31|1|0|K|K|ABC
LT|24|1|0|K|K|ABC|25|1|0|K|K|ABC|32|1|0|K|K|ABC
LE|25|1|0|K|K|ABC|26|1|0|K|K|ABC|33|1|0|K|K|ABC
TEST|26|1|1|R|U|ABC|27|1|0|N|U|ABC|34|1|0|N|U|ABC
TESTSET|27|1|1|R|U|ABC|28|1|1|R|U|ABC|35|1|1|R|U|ABC
CALL|28|0|1|U|U|ABC|29|0|1|U|U|ABC|36|0|1|U|U|ABC
TAILCALL|29|0|1|U|U|ABC|30|0|1|U|U|ABC|37|0|1|U|U|ABC
RETURN|30|0|0|U|N|ABC|31|0|0|U|N|ABC|38|0|0|U|N|ABC
FORLOOP|31|0|1|R|N|AsBx|32|0|1|R|N|AsBx|39|0|1|R|N|AsBx
FORPREP|32|0|1|R|N|AsBx|33|0|1|R|N|AsBx|40|0|1|R|N|AsBx
TFORCALL|||||||34|0|0|N|U|ABC|41|0|0|N|U|ABC
TFORLOOP|33|1|0|N|U|ABC|35|0|1|R|N|AsBx|42|0|1|R|N|AsBx
SETLIST|34|0|0|U|U|ABC|36|0|0|U|U|ABC|43|0|0|U|U|ABC
CLOSURE|36|0|1|U|N|ABx|37|0|1|U|N|ABx|44|0|1|U|N|ABx
VARARG|37|0|1|U|N|ABC|38|0|1|U|N|ABC|45|0|1|U|N|ABC
EXTRAARG|||||||39|0|0|U|U|Ax|46|0|0|U|U|Ax
GETGLOBAL|5|0|1|K|N|ABx||||||||||||
SETGLOBAL|7|0|0|K|N|ABx||||||||||||
CLOSE|35|0|0|N|N|ABC||||||||||||

Mask|Description
----|----
N|argument is not used
U|argument is used
R|argument is a register or a jump offset
K|argument is a constant or register/constant
